aiocmdline/__init__.py
aiocmdline/aiocmdline.py
aiocmdline-2024.1.25.dist-info/LICENSE.txt
aiocmdline-2024.1.25.dist-info/METADATA
aiocmdline-2024.1.25.dist-info/WHEEL
aiocmdline-2024.1.25.dist-info/top_level.txt
aiocmdline-2024.1.25.dist-info/RECORD
