Metadata-Version: 2.1
Name: aiocmdline
Version: 2024.1.25
Summary: Python class to build async-compatible line-oriented command interpreter
Author-email: Mario Kicherer <dev@kicherer.org>
License: Permission is hereby granted, free of charge, to any person obtaining a copy
Project-URL: Homepage, https://github.com/anyc/aiocmdline/
Project-URL: Issues, https://github.com/anyc/aiocmdline/issues
Keywords: cmdline,readline
Classifier: Programming Language :: Python :: 3
Requires-Python: >=3.0
License-File: LICENSE.txt
Requires-Dist: aioreadline
